{
  "generated_at": "2026-06-24T22:49:21.907299+00:00",
  "total_scored": 83,
  "high_quality_count": 11,
  "high_quality": [
    {
      "symbol": "INHD",
      "stars": 5,
      "close": 39.49,
      "adr_pct": 10.59,
      "dollar_volume": 550752304.0,
      "momentum_22": 39.099,
      "momentum_67": 533.6486,
      "momentum_126": 630.8307,
      "breakdown": {
        "ma_aligned": true,
        "higher_lows": true,
        "range_tightening": true,
        "narrow_candle": true,
        "volume_dryup": true,
        "rs_vs_spy_1m": 30.625,
        "sma10": 39.49,
        "sma20": 22.27,
        "sma50": 9.41
      }
    },
    {
      "symbol": "MEC",
      "stars": 5,
      "close": 34.39,
      "adr_pct": 6.17,
      "dollar_volume": 21998295.0,
      "momentum_22": 1.4779,
      "momentum_67": 2.0842,
      "momentum_126": 2.0842,
      "breakdown": {
        "ma_aligned": true,
        "higher_lows": true,
        "range_tightening": true,
        "narrow_candle": true,
        "volume_dryup": true,
        "rs_vs_spy_1m": 1.321,
        "sma10": 34.69,
        "sma20": 32.85,
        "sma50": 27.11
      }
    },
    {
      "symbol": "BRUN",
      "stars": 5,
      "close": 34.26,
      "adr_pct": 13.68,
      "dollar_volume": 75657885.0,
      "momentum_22": 1.4474,
      "momentum_67": 3.223,
      "momentum_126": 3.2351,
      "breakdown": {
        "ma_aligned": true,
        "higher_lows": true,
        "range_tightening": true,
        "narrow_candle": true,
        "volume_dryup": true,
        "rs_vs_spy_1m": 1.234,
        "sma10": 34.03,
        "sma20": 33.73,
        "sma50": 25.05
      }
    },
    {
      "symbol": "APGE",
      "stars": 4,
      "close": 132.69,
      "adr_pct": 5.28,
      "dollar_volume": 628900323.0,
      "momentum_22": 1.7491,
      "momentum_67": 2.0345,
      "momentum_126": 2.1987,
      "breakdown": {
        "ma_aligned": true,
        "higher_lows": true,
        "range_tightening": true,
        "narrow_candle": true,
        "volume_dryup": false,
        "rs_vs_spy_1m": 1.64,
        "sma10": 100.89,
        "sma20": 91.73,
        "sma50": 87.53
      }
    },
    {
      "symbol": "VSXY",
      "stars": 4,
      "close": 80.64,
      "adr_pct": 5.77,
      "dollar_volume": 217100268.0,
      "momentum_22": 1.6112,
      "momentum_67": 1.9205,
      "momentum_126": 1.9205,
      "breakdown": {
        "ma_aligned": true,
        "higher_lows": true,
        "range_tightening": true,
        "narrow_candle": false,
        "volume_dryup": true,
        "rs_vs_spy_1m": 1.476,
        "sma10": 79.05,
        "sma20": 73.72,
        "sma50": 59.63
      }
    },
    {
      "symbol": "TNGX",
      "stars": 4,
      "close": 29.12,
      "adr_pct": 8.09,
      "dollar_volume": 162478274.0,
      "momentum_22": 1.4989,
      "momentum_67": 1.5775,
      "momentum_126": 3.5084,
      "breakdown": {
        "ma_aligned": true,
        "higher_lows": true,
        "range_tightening": true,
        "narrow_candle": true,
        "volume_dryup": false,
        "rs_vs_spy_1m": 1.487,
        "sma10": 30.08,
        "sma20": 26.67,
        "sma50": 24.84
      }
    },
    {
      "symbol": "OSCR",
      "stars": 4,
      "close": 29.16,
      "adr_pct": 6.41,
      "dollar_volume": 188844374.0,
      "momentum_22": 1.4515,
      "momentum_67": 2.7278,
      "momentum_126": 2.7278,
      "breakdown": {
        "ma_aligned": true,
        "higher_lows": true,
        "range_tightening": true,
        "narrow_candle": false,
        "volume_dryup": true,
        "rs_vs_spy_1m": 1.364,
        "sma10": 28.7,
        "sma20": 26.04,
        "sma50": 22.2
      }
    },
    {
      "symbol": "CRDO",
      "stars": 4,
      "close": 268.99,
      "adr_pct": 10.26,
      "dollar_volume": 2397775542.0,
      "momentum_22": 1.3761,
      "momentum_67": 3.1103,
      "momentum_126": 3.1103,
      "breakdown": {
        "ma_aligned": true,
        "higher_lows": true,
        "range_tightening": true,
        "narrow_candle": false,
        "volume_dryup": true,
        "rs_vs_spy_1m": 1.242,
        "sma10": 261.65,
        "sma20": 242.34,
        "sma50": 206.96
      }
    },
    {
      "symbol": "AIP",
      "stars": 4,
      "close": 41.03,
      "adr_pct": 7.09,
      "dollar_volume": 39594904.0,
      "momentum_22": 1.2853,
      "momentum_67": 2.795,
      "momentum_126": 3.0348,
      "breakdown": {
        "ma_aligned": true,
        "higher_lows": true,
        "range_tightening": true,
        "narrow_candle": false,
        "volume_dryup": true,
        "rs_vs_spy_1m": 1.108,
        "sma10": 41.0,
        "sma20": 38.58,
        "sma50": 33.03
      }
    },
    {
      "symbol": "VPG",
      "stars": 4,
      "close": 133.39,
      "adr_pct": 8.91,
      "dollar_volume": 76743938.0,
      "momentum_22": 1.2817,
      "momentum_67": 3.4063,
      "momentum_126": 3.541,
      "breakdown": {
        "ma_aligned": true,
        "higher_lows": true,
        "range_tightening": true,
        "narrow_candle": false,
        "volume_dryup": true,
        "rs_vs_spy_1m": 1.106,
        "sma10": 137.12,
        "sma20": 131.26,
        "sma50": 96.4
      }
    },
    {
      "symbol": "WOLF",
      "stars": 4,
      "close": 45.87,
      "adr_pct": 15.69,
      "dollar_volume": 433920554.0,
      "momentum_22": 1.1465,
      "momentum_67": 3.1461,
      "momentum_126": 3.4016,
      "breakdown": {
        "ma_aligned": false,
        "higher_lows": true,
        "range_tightening": true,
        "narrow_candle": true,
        "volume_dryup": true,
        "rs_vs_spy_1m": 0.639,
        "sma10": 48.0,
        "sma20": 53.48,
        "sma50": 46.99
      }
    }
  ],
  "all_scored": [
    {
      "symbol": "INHD",
      "stars": 5,
      "close": 39.49,
      "adr_pct": 10.59,
      "dollar_volume": 550752304.0,
      "momentum_22": 39.099,
      "momentum_67": 533.6486,
      "momentum_126": 630.8307,
      "breakdown": {
        "ma_aligned": true,
        "higher_lows": true,
        "range_tightening": true,
        "narrow_candle": true,
        "volume_dryup": true,
        "rs_vs_spy_1m": 30.625,
        "sma10": 39.49,
        "sma20": 22.27,
        "sma50": 9.41
      }
    },
    {
      "symbol": "MEC",
      "stars": 5,
      "close": 34.39,
      "adr_pct": 6.17,
      "dollar_volume": 21998295.0,
      "momentum_22": 1.4779,
      "momentum_67": 2.0842,
      "momentum_126": 2.0842,
      "breakdown": {
        "ma_aligned": true,
        "higher_lows": true,
        "range_tightening": true,
        "narrow_candle": true,
        "volume_dryup": true,
        "rs_vs_spy_1m": 1.321,
        "sma10": 34.69,
        "sma20": 32.85,
        "sma50": 27.11
      }
    },
    {
      "symbol": "BRUN",
      "stars": 5,
      "close": 34.26,
      "adr_pct": 13.68,
      "dollar_volume": 75657885.0,
      "momentum_22": 1.4474,
      "momentum_67": 3.223,
      "momentum_126": 3.2351,
      "breakdown": {
        "ma_aligned": true,
        "higher_lows": true,
        "range_tightening": true,
        "narrow_candle": true,
        "volume_dryup": true,
        "rs_vs_spy_1m": 1.234,
        "sma10": 34.03,
        "sma20": 33.73,
        "sma50": 25.05
      }
    },
    {
      "symbol": "APGE",
      "stars": 4,
      "close": 132.69,
      "adr_pct": 5.28,
      "dollar_volume": 628900323.0,
      "momentum_22": 1.7491,
      "momentum_67": 2.0345,
      "momentum_126": 2.1987,
      "breakdown": {
        "ma_aligned": true,
        "higher_lows": true,
        "range_tightening": true,
        "narrow_candle": true,
        "volume_dryup": false,
        "rs_vs_spy_1m": 1.64,
        "sma10": 100.89,
        "sma20": 91.73,
        "sma50": 87.53
      }
    },
    {
      "symbol": "VSXY",
      "stars": 4,
      "close": 80.64,
      "adr_pct": 5.77,
      "dollar_volume": 217100268.0,
      "momentum_22": 1.6112,
      "momentum_67": 1.9205,
      "momentum_126": 1.9205,
      "breakdown": {
        "ma_aligned": true,
        "higher_lows": true,
        "range_tightening": true,
        "narrow_candle": false,
        "volume_dryup": true,
        "rs_vs_spy_1m": 1.476,
        "sma10": 79.05,
        "sma20": 73.72,
        "sma50": 59.63
      }
    },
    {
      "symbol": "TNGX",
      "stars": 4,
      "close": 29.12,
      "adr_pct": 8.09,
      "dollar_volume": 162478274.0,
      "momentum_22": 1.4989,
      "momentum_67": 1.5775,
      "momentum_126": 3.5084,
      "breakdown": {
        "ma_aligned": true,
        "higher_lows": true,
        "range_tightening": true,
        "narrow_candle": true,
        "volume_dryup": false,
        "rs_vs_spy_1m": 1.487,
        "sma10": 30.08,
        "sma20": 26.67,
        "sma50": 24.84
      }
    },
    {
      "symbol": "OSCR",
      "stars": 4,
      "close": 29.16,
      "adr_pct": 6.41,
      "dollar_volume": 188844374.0,
      "momentum_22": 1.4515,
      "momentum_67": 2.7278,
      "momentum_126": 2.7278,
      "breakdown": {
        "ma_aligned": true,
        "higher_lows": true,
        "range_tightening": true,
        "narrow_candle": false,
        "volume_dryup": true,
        "rs_vs_spy_1m": 1.364,
        "sma10": 28.7,
        "sma20": 26.04,
        "sma50": 22.2
      }
    },
    {
      "symbol": "CRDO",
      "stars": 4,
      "close": 268.99,
      "adr_pct": 10.26,
      "dollar_volume": 2397775542.0,
      "momentum_22": 1.3761,
      "momentum_67": 3.1103,
      "momentum_126": 3.1103,
      "breakdown": {
        "ma_aligned": true,
        "higher_lows": true,
        "range_tightening": true,
        "narrow_candle": false,
        "volume_dryup": true,
        "rs_vs_spy_1m": 1.242,
        "sma10": 261.65,
        "sma20": 242.34,
        "sma50": 206.96
      }
    },
    {
      "symbol": "AIP",
      "stars": 4,
      "close": 41.03,
      "adr_pct": 7.09,
      "dollar_volume": 39594904.0,
      "momentum_22": 1.2853,
      "momentum_67": 2.795,
      "momentum_126": 3.0348,
      "breakdown": {
        "ma_aligned": true,
        "higher_lows": true,
        "range_tightening": true,
        "narrow_candle": false,
        "volume_dryup": true,
        "rs_vs_spy_1m": 1.108,
        "sma10": 41.0,
        "sma20": 38.58,
        "sma50": 33.03
      }
    },
    {
      "symbol": "VPG",
      "stars": 4,
      "close": 133.39,
      "adr_pct": 8.91,
      "dollar_volume": 76743938.0,
      "momentum_22": 1.2817,
      "momentum_67": 3.4063,
      "momentum_126": 3.541,
      "breakdown": {
        "ma_aligned": true,
        "higher_lows": true,
        "range_tightening": true,
        "narrow_candle": false,
        "volume_dryup": true,
        "rs_vs_spy_1m": 1.106,
        "sma10": 137.12,
        "sma20": 131.26,
        "sma50": 96.4
      }
    },
    {
      "symbol": "WOLF",
      "stars": 4,
      "close": 45.87,
      "adr_pct": 15.69,
      "dollar_volume": 433920554.0,
      "momentum_22": 1.1465,
      "momentum_67": 3.1461,
      "momentum_126": 3.4016,
      "breakdown": {
        "ma_aligned": false,
        "higher_lows": true,
        "range_tightening": true,
        "narrow_candle": true,
        "volume_dryup": true,
        "rs_vs_spy_1m": 0.639,
        "sma10": 48.0,
        "sma20": 53.48,
        "sma50": 46.99
      }
    },
    {
      "symbol": "DLLL",
      "stars": 3,
      "close": 203.55,
      "adr_pct": 13.91,
      "dollar_volume": 99207586.0,
      "momentum_22": 2.3356,
      "momentum_67": 7.1121,
      "momentum_126": 11.7386,
      "breakdown": {
        "ma_aligned": true,
        "higher_lows": true,
        "range_tightening": false,
        "narrow_candle": false,
        "volume_dryup": true,
        "rs_vs_spy_1m": 1.862,
        "sma10": 181.15,
        "sma20": 179.87,
        "sma50": 111.1
      }
    },
    {
      "symbol": "HIMZ",
      "stars": 3,
      "close": 44.18,
      "adr_pct": 15.4,
      "dollar_volume": 23132796.0,
      "momentum_22": 1.8162,
      "momentum_67": 2.3714,
      "momentum_126": 49.9548,
      "breakdown": {
        "ma_aligned": true,
        "higher_lows": true,
        "range_tightening": false,
        "narrow_candle": false,
        "volume_dryup": true,
        "rs_vs_spy_1m": 1.783,
        "sma10": 41.09,
        "sma20": 36.6,
        "sma50": 34.85
      }
    },
    {
      "symbol": "MBX",
      "stars": 3,
      "close": 48.4,
      "adr_pct": 7.98,
      "dollar_volume": 31779129.0,
      "momentum_22": 1.7286,
      "momentum_67": 1.8516,
      "momentum_126": 1.8516,
      "breakdown": {
        "ma_aligned": true,
        "higher_lows": true,
        "range_tightening": false,
        "narrow_candle": false,
        "volume_dryup": true,
        "rs_vs_spy_1m": 1.56,
        "sma10": 40.61,
        "sma20": 35.64,
        "sma50": 33.97
      }
    },
    {
      "symbol": "MUU",
      "stars": 3,
      "close": 902.1,
      "adr_pct": 13.88,
      "dollar_volume": 3199743984.0,
      "momentum_22": 1.7052,
      "momentum_67": 8.8036,
      "momentum_126": 10.0421,
      "breakdown": {
        "ma_aligned": true,
        "higher_lows": true,
        "range_tightening": true,
        "narrow_candle": false,
        "volume_dryup": false,
        "rs_vs_spy_1m": 1.248,
        "sma10": 931.85,
        "sma20": 898.17,
        "sma50": 592.29
      }
    },
    {
      "symbol": "MRVU",
      "stars": 3,
      "close": 200.99,
      "adr_pct": 19.68,
      "dollar_volume": 126047105.0,
      "momentum_22": 1.7035,
      "momentum_67": 7.7722,
      "momentum_126": NaN,
      "breakdown": {
        "ma_aligned": false,
        "higher_lows": true,
        "range_tightening": true,
        "narrow_candle": false,
        "volume_dryup": true,
        "rs_vs_spy_1m": 1.494,
        "sma10": 220.92,
        "sma20": 209.5,
        "sma50": 137.95
      }
    },
    {
      "symbol": "LINT",
      "stars": 3,
      "close": 231.0,
      "adr_pct": 13.64,
      "dollar_volume": 38677036.0,
      "momentum_22": 1.7033,
      "momentum_67": 8.3333,
      "momentum_126": 9.0909,
      "breakdown": {
        "ma_aligned": true,
        "higher_lows": true,
        "range_tightening": true,
        "narrow_candle": false,
        "volume_dryup": false,
        "rs_vs_spy_1m": 1.077,
        "sma10": 213.77,
        "sma20": 195.83,
        "sma50": 167.62
      }
    },
    {
      "symbol": "INTW",
      "stars": 3,
      "close": 362.95,
      "adr_pct": 13.96,
      "dollar_volume": 237898609.0,
      "momentum_22": 1.6975,
      "momentum_67": 8.2489,
      "momentum_126": 9.3665,
      "breakdown": {
        "ma_aligned": true,
        "higher_lows": true,
        "range_tightening": true,
        "narrow_candle": false,
        "volume_dryup": false,
        "rs_vs_spy_1m": 1.071,
        "sma10": 337.0,
        "sma20": 308.82,
        "sma50": 264.71
      }
    },
    {
      "symbol": "MVLL",
      "stars": 3,
      "close": 149.82,
      "adr_pct": 19.86,
      "dollar_volume": 621380916.0,
      "momentum_22": 1.674,
      "momentum_67": 7.5552,
      "momentum_126": 10.3503,
      "breakdown": {
        "ma_aligned": false,
        "higher_lows": true,
        "range_tightening": true,
        "narrow_candle": false,
        "volume_dryup": true,
        "rs_vs_spy_1m": 1.469,
        "sma10": 166.03,
        "sma20": 157.99,
        "sma50": 104.61
      }
    },
    {
      "symbol": "ALHC",
      "stars": 3,
      "close": 21.69,
      "adr_pct": 6.13,
      "dollar_volume": 118868092.0,
      "momentum_22": 1.6621,
      "momentum_67": 1.6621,
      "momentum_126": 1.6621,
      "breakdown": {
        "ma_aligned": false,
        "higher_lows": true,
        "range_tightening": true,
        "narrow_candle": false,
        "volume_dryup": true,
        "rs_vs_spy_1m": 1.385,
        "sma10": 20.88,
        "sma20": 18.11,
        "sma50": 18.72
      }
    },
    {
      "symbol": "DELL",
      "stars": 3,
      "close": 434.06,
      "adr_pct": 7.15,
      "dollar_volume": 5062970641.0,
      "momentum_22": 1.6367,
      "momentum_67": 2.9615,
      "momentum_126": 3.9381,
      "breakdown": {
        "ma_aligned": true,
        "higher_lows": true,
        "range_tightening": false,
        "narrow_candle": false,
        "volume_dryup": true,
        "rs_vs_spy_1m": 1.456,
        "sma10": 407.94,
        "sma20": 402.2,
        "sma50": 296.96
      }
    },
    {
      "symbol": "CBRL",
      "stars": 3,
      "close": 48.38,
      "adr_pct": 5.59,
      "dollar_volume": 71857494.0,
      "momentum_22": 1.5173,
      "momentum_67": 1.8361,
      "momentum_126": 1.9469,
      "breakdown": {
        "ma_aligned": true,
        "higher_lows": true,
        "range_tightening": false,
        "narrow_candle": false,
        "volume_dryup": true,
        "rs_vs_spy_1m": 1.487,
        "sma10": 45.61,
        "sma20": 39.91,
        "sma50": 34.17
      }
    },
    {
      "symbol": "PDFS",
      "stars": 3,
      "close": 63.56,
      "adr_pct": 6.62,
      "dollar_volume": 45984535.0,
      "momentum_22": 1.4406,
      "momentum_67": 2.0704,
      "momentum_126": 2.3908,
      "breakdown": {
        "ma_aligned": true,
        "higher_lows": true,
        "range_tightening": true,
        "narrow_candle": false,
        "volume_dryup": false,
        "rs_vs_spy_1m": 1.329,
        "sma10": 62.77,
        "sma20": 57.89,
        "sma50": 50.28
      }
    },
    {
      "symbol": "MRVL",
      "stars": 3,
      "close": 276.7,
      "adr_pct": 9.9,
      "dollar_volume": 20553036848.0,
      "momentum_22": 1.4395,
      "momentum_67": 3.2503,
      "momentum_126": 3.9146,
      "breakdown": {
        "ma_aligned": true,
        "higher_lows": true,
        "range_tightening": true,
        "narrow_candle": false,
        "volume_dryup": false,
        "rs_vs_spy_1m": 1.36,
        "sma10": 286.43,
        "sma20": 271.01,
        "sma50": 207.62
      }
    },
    {
      "symbol": "DAVE",
      "stars": 3,
      "close": 323.22,
      "adr_pct": 8.09,
      "dollar_volume": 216381693.0,
      "momentum_22": 1.4378,
      "momentum_67": 1.9709,
      "momentum_126": 2.1235,
      "breakdown": {
        "ma_aligned": true,
        "higher_lows": true,
        "range_tightening": false,
        "narrow_candle": false,
        "volume_dryup": true,
        "rs_vs_spy_1m": 1.327,
        "sma10": 300.16,
        "sma20": 283.84,
        "sma50": 265.51
      }
    },
    {
      "symbol": "AGL",
      "stars": 3,
      "close": 106.96,
      "adr_pct": 8.99,
      "dollar_volume": 28408672.0,
      "momentum_22": 1.4347,
      "momentum_67": 351.8421,
      "momentum_126": 351.8421,
      "breakdown": {
        "ma_aligned": true,
        "higher_lows": true,
        "range_tightening": true,
        "narrow_candle": false,
        "volume_dryup": false,
        "rs_vs_spy_1m": 1.284,
        "sma10": 110.87,
        "sma20": 101.65,
        "sma50": 69.64
      }
    },
    {
      "symbol": "ICHR",
      "stars": 3,
      "close": 89.38,
      "adr_pct": 7.94,
      "dollar_volume": 93311233.0,
      "momentum_22": 1.4315,
      "momentum_67": 2.1496,
      "momentum_126": 5.0578,
      "breakdown": {
        "ma_aligned": true,
        "higher_lows": true,
        "range_tightening": true,
        "narrow_candle": false,
        "volume_dryup": false,
        "rs_vs_spy_1m": 1.258,
        "sma10": 88.75,
        "sma20": 79.63,
        "sma50": 72.95
      }
    },
    {
      "symbol": "MU",
      "stars": 3,
      "close": 1048.51,
      "adr_pct": 7.11,
      "dollar_volume": 56127345126.0,
      "momentum_22": 1.4033,
      "momentum_67": 3.3661,
      "momentum_126": 3.9081,
      "breakdown": {
        "ma_aligned": true,
        "higher_lows": true,
        "range_tightening": true,
        "narrow_candle": false,
        "volume_dryup": false,
        "rs_vs_spy_1m": 1.198,
        "sma10": 1046.7,
        "sma20": 1010.71,
        "sma50": 773.66
      }
    },
    {
      "symbol": "ARMG",
      "stars": 3,
      "close": 40.71,
      "adr_pct": 19.14,
      "dollar_volume": 118027103.0,
      "momentum_22": 1.3842,
      "momentum_67": 5.9292,
      "momentum_126": 8.7832,
      "breakdown": {
        "ma_aligned": false,
        "higher_lows": true,
        "range_tightening": true,
        "narrow_candle": false,
        "volume_dryup": true,
        "rs_vs_spy_1m": 1.116,
        "sma10": 48.09,
        "sma20": 47.07,
        "sma50": 29.93
      }
    },
    {
      "symbol": "AMDL",
      "stars": 3,
      "close": 66.74,
      "adr_pct": 11.54,
      "dollar_volume": 333514171.0,
      "momentum_22": 1.3832,
      "momentum_67": 6.07,
      "momentum_126": 6.1796,
      "breakdown": {
        "ma_aligned": false,
        "higher_lows": true,
        "range_tightening": true,
        "narrow_candle": false,
        "volume_dryup": true,
        "rs_vs_spy_1m": 1.021,
        "sma10": 66.54,
        "sma20": 66.7,
        "sma50": 50.49
      }
    },
    {
      "symbol": "ALAB",
      "stars": 3,
      "close": 399.92,
      "adr_pct": 8.68,
      "dollar_volume": 2379468478.0,
      "momentum_22": 1.3767,
      "momentum_67": 4.0854,
      "momentum_126": 4.0854,
      "breakdown": {
        "ma_aligned": true,
        "higher_lows": true,
        "range_tightening": true,
        "narrow_candle": false,
        "volume_dryup": false,
        "rs_vs_spy_1m": 1.284,
        "sma10": 384.47,
        "sma20": 363.23,
        "sma50": 273.86
      }
    },
    {
      "symbol": "AMUU",
      "stars": 3,
      "close": 234.92,
      "adr_pct": 10.81,
      "dollar_volume": 30554275.0,
      "momentum_22": 1.3689,
      "momentum_67": 6.0921,
      "momentum_126": 6.1903,
      "breakdown": {
        "ma_aligned": false,
        "higher_lows": true,
        "range_tightening": true,
        "narrow_candle": false,
        "volume_dryup": true,
        "rs_vs_spy_1m": 1.028,
        "sma10": 233.92,
        "sma20": 234.04,
        "sma50": 176.88
      }
    },
    {
      "symbol": "UCTT",
      "stars": 3,
      "close": 108.42,
      "adr_pct": 7.63,
      "dollar_volume": 132357522.0,
      "momentum_22": 1.3553,
      "momentum_67": 1.9879,
      "momentum_126": 4.2871,
      "breakdown": {
        "ma_aligned": true,
        "higher_lows": true,
        "range_tightening": true,
        "narrow_candle": false,
        "volume_dryup": false,
        "rs_vs_spy_1m": 1.269,
        "sma10": 110.36,
        "sma20": 99.35,
        "sma50": 87.92
      }
    },
    {
      "symbol": "SIMO",
      "stars": 3,
      "close": 321.66,
      "adr_pct": 7.93,
      "dollar_volume": 297459432.0,
      "momentum_22": 1.345,
      "momentum_67": 3.0637,
      "momentum_126": 3.6561,
      "breakdown": {
        "ma_aligned": true,
        "higher_lows": true,
        "range_tightening": true,
        "narrow_candle": false,
        "volume_dryup": false,
        "rs_vs_spy_1m": 1.134,
        "sma10": 297.19,
        "sma20": 288.42,
        "sma50": 242.05
      }
    },
    {
      "symbol": "INTC",
      "stars": 3,
      "close": 131.65,
      "adr_pct": 7.06,
      "dollar_volume": 16022434936.0,
      "momentum_22": 1.3389,
      "momentum_67": 3.2402,
      "momentum_126": 3.7668,
      "breakdown": {
        "ma_aligned": true,
        "higher_lows": true,
        "range_tightening": true,
        "narrow_candle": false,
        "volume_dryup": false,
        "rs_vs_spy_1m": 1.091,
        "sma10": 125.34,
        "sma20": 118.49,
        "sma50": 105.74
      }
    },
    {
      "symbol": "ATEX",
      "stars": 3,
      "close": 79.09,
      "adr_pct": 7.94,
      "dollar_volume": 39284447.0,
      "momentum_22": 1.3182,
      "momentum_67": 2.2756,
      "momentum_126": 3.7519,
      "breakdown": {
        "ma_aligned": true,
        "higher_lows": true,
        "range_tightening": true,
        "narrow_candle": false,
        "volume_dryup": false,
        "rs_vs_spy_1m": 1.27,
        "sma10": 77.91,
        "sma20": 71.82,
        "sma50": 59.09
      }
    },
    {
      "symbol": "SNDK",
      "stars": 3,
      "close": 1914.46,
      "adr_pct": 7.77,
      "dollar_volume": 19924627948.0,
      "momentum_22": 1.2992,
      "momentum_67": 3.4274,
      "momentum_126": 8.4486,
      "breakdown": {
        "ma_aligned": true,
        "higher_lows": true,
        "range_tightening": true,
        "narrow_candle": false,
        "volume_dryup": false,
        "rs_vs_spy_1m": 1.233,
        "sma10": 1989.96,
        "sma20": 1837.15,
        "sma50": 1469.77
      }
    },
    {
      "symbol": "MXL",
      "stars": 3,
      "close": 84.99,
      "adr_pct": 10.68,
      "dollar_volume": 357803652.0,
      "momentum_22": 1.2541,
      "momentum_67": 5.3605,
      "momentum_126": 5.7816,
      "breakdown": {
        "ma_aligned": false,
        "higher_lows": true,
        "range_tightening": true,
        "narrow_candle": false,
        "volume_dryup": true,
        "rs_vs_spy_1m": 0.905,
        "sma10": 85.28,
        "sma20": 86.9,
        "sma50": 76.09
      }
    },
    {
      "symbol": "AEHR",
      "stars": 3,
      "close": 95.2,
      "adr_pct": 11.39,
      "dollar_volume": 192443021.0,
      "momentum_22": 1.1251,
      "momentum_67": 3.2681,
      "momentum_126": 4.7839,
      "breakdown": {
        "ma_aligned": false,
        "higher_lows": true,
        "range_tightening": true,
        "narrow_candle": false,
        "volume_dryup": true,
        "rs_vs_spy_1m": 0.887,
        "sma10": 106.44,
        "sma20": 104.33,
        "sma50": 96.47
      }
    },
    {
      "symbol": "APPX",
      "stars": 3,
      "close": 33.31,
      "adr_pct": 12.18,
      "dollar_volume": 24947515.0,
      "momentum_22": 1.0766,
      "momentum_67": 1.4668,
      "momentum_126": 4.1073,
      "breakdown": {
        "ma_aligned": false,
        "higher_lows": false,
        "range_tightening": true,
        "narrow_candle": true,
        "volume_dryup": true,
        "rs_vs_spy_1m": 0.802,
        "sma10": 36.57,
        "sma20": 44.68,
        "sma50": 40.05
      }
    },
    {
      "symbol": "HQ",
      "stars": 2,
      "close": 28.41,
      "adr_pct": 18.12,
      "dollar_volume": 34638780.0,
      "momentum_22": 2.9138,
      "momentum_67": NaN,
      "momentum_126": NaN,
      "breakdown": {
        "ma_aligned": true,
        "higher_lows": true,
        "range_tightening": false,
        "narrow_candle": false,
        "volume_dryup": false,
        "rs_vs_spy_1m": 2.456,
        "sma10": 22.36,
        "sma20": 17.27,
        "sma50": 13.71
      }
    },
    {
      "symbol": "ARQQ",
      "stars": 2,
      "close": 28.64,
      "adr_pct": 13.82,
      "dollar_volume": 29849295.0,
      "momentum_22": 2.4271,
      "momentum_67": 2.4861,
      "momentum_126": 2.4861,
      "breakdown": {
        "ma_aligned": true,
        "higher_lows": true,
        "range_tightening": false,
        "narrow_candle": false,
        "volume_dryup": false,
        "rs_vs_spy_1m": 1.767,
        "sma10": 20.43,
        "sma20": 17.67,
        "sma50": 15.92
      }
    },
    {
      "symbol": "QURE",
      "stars": 2,
      "close": 48.85,
      "adr_pct": 7.29,
      "dollar_volume": 114640861.0,
      "momentum_22": 2.0354,
      "momentum_67": 3.698,
      "momentum_126": 5.5956,
      "breakdown": {
        "ma_aligned": true,
        "higher_lows": true,
        "range_tightening": false,
        "narrow_candle": false,
        "volume_dryup": false,
        "rs_vs_spy_1m": 1.988,
        "sma10": 37.28,
        "sma20": 32.21,
        "sma50": 25.98
      }
    },
    {
      "symbol": "DFTX",
      "stars": 2,
      "close": 42.13,
      "adr_pct": 6.95,
      "dollar_volume": 120129070.0,
      "momentum_22": 1.9424,
      "momentum_67": 2.4594,
      "momentum_126": 3.3331,
      "breakdown": {
        "ma_aligned": true,
        "higher_lows": true,
        "range_tightening": false,
        "narrow_candle": false,
        "volume_dryup": false,
        "rs_vs_spy_1m": 1.885,
        "sma10": 28.39,
        "sma20": 25.99,
        "sma50": 23.6
      }
    },
    {
      "symbol": "WYFI",
      "stars": 2,
      "close": 38.71,
      "adr_pct": 13.08,
      "dollar_volume": 74277838.0,
      "momentum_22": 1.7768,
      "momentum_67": 3.6831,
      "momentum_126": 3.6831,
      "breakdown": {
        "ma_aligned": true,
        "higher_lows": true,
        "range_tightening": false,
        "narrow_candle": false,
        "volume_dryup": false,
        "rs_vs_spy_1m": 1.261,
        "sma10": 33.8,
        "sma20": 30.93,
        "sma50": 24.89
      }
    },
    {
      "symbol": "CDNL",
      "stars": 2,
      "close": 81.94,
      "adr_pct": 8.6,
      "dollar_volume": 36849454.0,
      "momentum_22": 1.7595,
      "momentum_67": 2.8152,
      "momentum_126": 3.7279,
      "breakdown": {
        "ma_aligned": true,
        "higher_lows": true,
        "range_tightening": false,
        "narrow_candle": false,
        "volume_dryup": false,
        "rs_vs_spy_1m": 1.596,
        "sma10": 72.72,
        "sma20": 65.06,
        "sma50": 57.01
      }
    },
    {
      "symbol": "MULL",
      "stars": 2,
      "close": 780.12,
      "adr_pct": 13.62,
      "dollar_volume": 328348403.0,
      "momentum_22": 1.6849,
      "momentum_67": 8.6159,
      "momentum_126": 9.6879,
      "breakdown": {
        "ma_aligned": false,
        "higher_lows": true,
        "range_tightening": true,
        "narrow_candle": false,
        "volume_dryup": false,
        "rs_vs_spy_1m": 1.231,
        "sma10": 811.29,
        "sma20": 783.11,
        "sma50": 517.55
      }
    },
    {
      "symbol": "HOOG",
      "stars": 2,
      "close": 28.46,
      "adr_pct": 14.47,
      "dollar_volume": 24409691.0,
      "momentum_22": 1.6406,
      "momentum_67": 1.9726,
      "momentum_126": 1.9726,
      "breakdown": {
        "ma_aligned": true,
        "higher_lows": true,
        "range_tightening": false,
        "narrow_candle": false,
        "volume_dryup": false,
        "rs_vs_spy_1m": 1.64,
        "sma10": 29.76,
        "sma20": 26.45,
        "sma50": 23.43
      }
    },
    {
      "symbol": "NBIG",
      "stars": 2,
      "close": 35.7,
      "adr_pct": 20.03,
      "dollar_volume": 35027146.0,
      "momentum_22": 1.6361,
      "momentum_67": 6.4909,
      "momentum_126": 7.9157,
      "breakdown": {
        "ma_aligned": true,
        "higher_lows": true,
        "range_tightening": false,
        "narrow_candle": false,
        "volume_dryup": false,
        "rs_vs_spy_1m": 1.461,
        "sma10": 35.94,
        "sma20": 33.81,
        "sma50": 25.3
      }
    },
    {
      "symbol": "NBIL",
      "stars": 2,
      "close": 51.08,
      "adr_pct": 20.0,
      "dollar_volume": 74395395.0,
      "momentum_22": 1.6346,
      "momentum_67": 6.5571,
      "momentum_126": 8.0188,
      "breakdown": {
        "ma_aligned": true,
        "higher_lows": true,
        "range_tightening": false,
        "narrow_candle": false,
        "volume_dryup": false,
        "rs_vs_spy_1m": 1.463,
        "sma10": 51.56,
        "sma20": 48.48,
        "sma50": 36.19
      }
    },
    {
      "symbol": "TWST",
      "stars": 2,
      "close": 91.35,
      "adr_pct": 6.94,
      "dollar_volume": 159275350.0,
      "momentum_22": 1.6203,
      "momentum_67": 2.2001,
      "momentum_126": 2.9468,
      "breakdown": {
        "ma_aligned": true,
        "higher_lows": true,
        "range_tightening": false,
        "narrow_candle": false,
        "volume_dryup": false,
        "rs_vs_spy_1m": 1.442,
        "sma10": 81.57,
        "sma20": 75.47,
        "sma50": 64.75
      }
    },
    {
      "symbol": "SEZL",
      "stars": 2,
      "close": 159.27,
      "adr_pct": 6.61,
      "dollar_volume": 90481341.0,
      "momentum_22": 1.5732,
      "momentum_67": 2.8085,
      "momentum_126": 2.8958,
      "breakdown": {
        "ma_aligned": true,
        "higher_lows": true,
        "range_tightening": false,
        "narrow_candle": false,
        "volume_dryup": false,
        "rs_vs_spy_1m": 1.482,
        "sma10": 145.02,
        "sma20": 131.86,
        "sma50": 106.72
      }
    },
    {
      "symbol": "ALNT",
      "stars": 2,
      "close": 97.97,
      "adr_pct": 6.25,
      "dollar_volume": 25808470.0,
      "momentum_22": 1.566,
      "momentum_67": 1.7119,
      "momentum_126": 1.8393,
      "breakdown": {
        "ma_aligned": true,
        "higher_lows": true,
        "range_tightening": false,
        "narrow_candle": false,
        "volume_dryup": false,
        "rs_vs_spy_1m": 1.406,
        "sma10": 94.15,
        "sma20": 88.74,
        "sma50": 77.25
      }
    },
    {
      "symbol": "EPC",
      "stars": 2,
      "close": 26.58,
      "adr_pct": 5.12,
      "dollar_volume": 23876908.0,
      "momentum_22": 1.5635,
      "momentum_67": 1.6903,
      "momentum_126": 1.6903,
      "breakdown": {
        "ma_aligned": true,
        "higher_lows": true,
        "range_tightening": false,
        "narrow_candle": false,
        "volume_dryup": false,
        "rs_vs_spy_1m": 1.553,
        "sma10": 23.3,
        "sma20": 21.07,
        "sma50": 20.85
      }
    },
    {
      "symbol": "UMC",
      "stars": 2,
      "close": 28.01,
      "adr_pct": 5.24,
      "dollar_volume": 448663944.0,
      "momentum_22": 1.5578,
      "momentum_67": 3.3788,
      "momentum_126": 3.64,
      "breakdown": {
        "ma_aligned": true,
        "higher_lows": true,
        "range_tightening": false,
        "narrow_candle": false,
        "volume_dryup": false,
        "rs_vs_spy_1m": 1.36,
        "sma10": 23.35,
        "sma20": 22.38,
        "sma50": 17.57
      }
    },
    {
      "symbol": "ORKA",
      "stars": 2,
      "close": 82.09,
      "adr_pct": 6.24,
      "dollar_volume": 93683162.0,
      "momentum_22": 1.531,
      "momentum_67": 2.186,
      "momentum_126": 3.2537,
      "breakdown": {
        "ma_aligned": true,
        "higher_lows": true,
        "range_tightening": false,
        "narrow_candle": false,
        "volume_dryup": false,
        "rs_vs_spy_1m": 1.423,
        "sma10": 73.3,
        "sma20": 66.42,
        "sma50": 65.98
      }
    },
    {
      "symbol": "TXG",
      "stars": 2,
      "close": 34.6,
      "adr_pct": 7.85,
      "dollar_volume": 105178916.0,
      "momentum_22": 1.5024,
      "momentum_67": 2.0534,
      "momentum_126": 2.1761,
      "breakdown": {
        "ma_aligned": true,
        "higher_lows": true,
        "range_tightening": false,
        "narrow_candle": false,
        "volume_dryup": false,
        "rs_vs_spy_1m": 1.439,
        "sma10": 31.73,
        "sma20": 30.79,
        "sma50": 25.92
      }
    },
    {
      "symbol": "SHAZ",
      "stars": 2,
      "close": 83.69,
      "adr_pct": 13.41,
      "dollar_volume": 79947657.0,
      "momentum_22": 1.4779,
      "momentum_67": 3.9532,
      "momentum_126": NaN,
      "breakdown": {
        "ma_aligned": true,
        "higher_lows": true,
        "range_tightening": false,
        "narrow_candle": false,
        "volume_dryup": false,
        "rs_vs_spy_1m": 1.318,
        "sma10": 78.13,
        "sma20": 75.4,
        "sma50": 58.85
      }
    },
    {
      "symbol": "TGTX",
      "stars": 2,
      "close": 53.6,
      "adr_pct": 4.93,
      "dollar_volume": 128603342.0,
      "momentum_22": 1.4695,
      "momentum_67": 1.8408,
      "momentum_126": 2.003,
      "breakdown": {
        "ma_aligned": true,
        "higher_lows": true,
        "range_tightening": false,
        "narrow_candle": false,
        "volume_dryup": false,
        "rs_vs_spy_1m": 1.381,
        "sma10": 51.17,
        "sma20": 45.34,
        "sma50": 40.93
      }
    },
    {
      "symbol": "ACMR",
      "stars": 2,
      "close": 101.6,
      "adr_pct": 9.43,
      "dollar_volume": 168230414.0,
      "momentum_22": 1.4564,
      "momentum_67": 2.7341,
      "momentum_126": 2.7341,
      "breakdown": {
        "ma_aligned": true,
        "higher_lows": true,
        "range_tightening": false,
        "narrow_candle": false,
        "volume_dryup": false,
        "rs_vs_spy_1m": 1.203,
        "sma10": 96.2,
        "sma20": 91.06,
        "sma50": 71.43
      }
    },
    {
      "symbol": "CXW",
      "stars": 2,
      "close": 29.8,
      "adr_pct": 4.27,
      "dollar_volume": 35809912.0,
      "momentum_22": 1.4351,
      "momentum_67": 1.6143,
      "momentum_126": 1.8939,
      "breakdown": {
        "ma_aligned": true,
        "higher_lows": true,
        "range_tightening": false,
        "narrow_candle": false,
        "volume_dryup": false,
        "rs_vs_spy_1m": 1.44,
        "sma10": 28.23,
        "sma20": 25.34,
        "sma50": 22.48
      }
    },
    {
      "symbol": "ELVN",
      "stars": 2,
      "close": 47.77,
      "adr_pct": 7.12,
      "dollar_volume": 84210078.0,
      "momentum_22": 1.4281,
      "momentum_67": 1.7878,
      "momentum_126": 3.231,
      "breakdown": {
        "ma_aligned": false,
        "higher_lows": true,
        "range_tightening": true,
        "narrow_candle": false,
        "volume_dryup": false,
        "rs_vs_spy_1m": 1.15,
        "sma10": 44.07,
        "sma20": 40.57,
        "sma50": 41.9
      }
    },
    {
      "symbol": "BE",
      "stars": 2,
      "close": 326.19,
      "adr_pct": 8.19,
      "dollar_volume": 3143686595.0,
      "momentum_22": 1.4145,
      "momentum_67": 2.7998,
      "momentum_126": 3.8768,
      "breakdown": {
        "ma_aligned": true,
        "higher_lows": true,
        "range_tightening": false,
        "narrow_candle": false,
        "volume_dryup": false,
        "rs_vs_spy_1m": 1.104,
        "sma10": 290.66,
        "sma20": 285.36,
        "sma50": 271.13
      }
    },
    {
      "symbol": "WDC",
      "stars": 2,
      "close": 643.83,
      "adr_pct": 6.63,
      "dollar_volume": 5615809255.0,
      "momentum_22": 1.3454,
      "momentum_67": 2.585,
      "momentum_126": 3.7594,
      "breakdown": {
        "ma_aligned": true,
        "higher_lows": true,
        "range_tightening": false,
        "narrow_candle": false,
        "volume_dryup": false,
        "rs_vs_spy_1m": 1.256,
        "sma10": 642.25,
        "sma20": 592.54,
        "sma50": 500.3
      }
    },
    {
      "symbol": "PENG",
      "stars": 2,
      "close": 64.72,
      "adr_pct": 11.12,
      "dollar_volume": 202839587.0,
      "momentum_22": 1.3227,
      "momentum_67": 4.0349,
      "momentum_126": 4.0349,
      "breakdown": {
        "ma_aligned": true,
        "higher_lows": true,
        "range_tightening": false,
        "narrow_candle": false,
        "volume_dryup": false,
        "rs_vs_spy_1m": 1.206,
        "sma10": 63.77,
        "sma20": 63.06,
        "sma50": 47.5
      }
    },
    {
      "symbol": "NBIS",
      "stars": 2,
      "close": 259.66,
      "adr_pct": 10.16,
      "dollar_volume": 4630804424.0,
      "momentum_22": 1.3094,
      "momentum_67": 2.8963,
      "momentum_126": 3.5318,
      "breakdown": {
        "ma_aligned": true,
        "higher_lows": true,
        "range_tightening": false,
        "narrow_candle": false,
        "volume_dryup": false,
        "rs_vs_spy_1m": 1.278,
        "sma10": 257.76,
        "sma20": 247.29,
        "sma50": 204.85
      }
    },
    {
      "symbol": "ARM",
      "stars": 2,
      "close": 359.08,
      "adr_pct": 9.64,
      "dollar_volume": 5067722119.0,
      "momentum_22": 1.2459,
      "momentum_67": 2.8842,
      "momentum_126": 3.5901,
      "breakdown": {
        "ma_aligned": false,
        "higher_lows": true,
        "range_tightening": true,
        "narrow_candle": false,
        "volume_dryup": false,
        "rs_vs_spy_1m": 1.144,
        "sma10": 383.09,
        "sma20": 372.66,
        "sma50": 278.07
      }
    },
    {
      "symbol": "STX",
      "stars": 2,
      "close": 993.25,
      "adr_pct": 6.3,
      "dollar_volume": 3981019060.0,
      "momentum_22": 1.2419,
      "momentum_67": 2.8264,
      "momentum_126": 3.6214,
      "breakdown": {
        "ma_aligned": true,
        "higher_lows": true,
        "range_tightening": false,
        "narrow_candle": false,
        "volume_dryup": false,
        "rs_vs_spy_1m": 1.202,
        "sma10": 992.74,
        "sma20": 942.17,
        "sma50": 792.96
      }
    },
    {
      "symbol": "HUT",
      "stars": 2,
      "close": 116.1,
      "adr_pct": 8.69,
      "dollar_volume": 479180212.0,
      "momentum_22": 1.1444,
      "momentum_67": 2.7603,
      "momentum_126": 2.7603,
      "breakdown": {
        "ma_aligned": false,
        "higher_lows": true,
        "range_tightening": true,
        "narrow_candle": false,
        "volume_dryup": false,
        "rs_vs_spy_1m": 1.056,
        "sma10": 118.35,
        "sma20": 120.96,
        "sma50": 101.56
      }
    },
    {
      "symbol": "AMBQ",
      "stars": 2,
      "close": 81.18,
      "adr_pct": 8.28,
      "dollar_volume": 62650562.0,
      "momentum_22": 1.1125,
      "momentum_67": 3.5684,
      "momentum_126": 3.5684,
      "breakdown": {
        "ma_aligned": false,
        "higher_lows": true,
        "range_tightening": true,
        "narrow_candle": false,
        "volume_dryup": false,
        "rs_vs_spy_1m": 0.995,
        "sma10": 82.99,
        "sma20": 81.54,
        "sma50": 62.19
      }
    },
    {
      "symbol": "BAND",
      "stars": 2,
      "close": 52.28,
      "adr_pct": 9.31,
      "dollar_volume": 93602431.0,
      "momentum_22": 1.0858,
      "momentum_67": 3.5134,
      "momentum_126": 4.1824,
      "breakdown": {
        "ma_aligned": false,
        "higher_lows": false,
        "range_tightening": true,
        "narrow_candle": true,
        "volume_dryup": false,
        "rs_vs_spy_1m": 0.875,
        "sma10": 55.16,
        "sma20": 60.62,
        "sma50": 48.16
      }
    },
    {
      "symbol": "AAOI",
      "stars": 2,
      "close": 146.97,
      "adr_pct": 12.97,
      "dollar_volume": 2485199078.0,
      "momentum_22": 1.0673,
      "momentum_67": 1.8704,
      "momentum_126": 4.6407,
      "breakdown": {
        "ma_aligned": false,
        "higher_lows": false,
        "range_tightening": true,
        "narrow_candle": true,
        "volume_dryup": false,
        "rs_vs_spy_1m": 0.847,
        "sma10": 167.42,
        "sma20": 174.65,
        "sma50": 170.41
      }
    },
    {
      "symbol": "IONX",
      "stars": 2,
      "close": 52.28,
      "adr_pct": 18.36,
      "dollar_volume": 95251940.0,
      "momentum_22": 1.0536,
      "momentum_67": 3.1101,
      "momentum_126": 6.2238,
      "breakdown": {
        "ma_aligned": false,
        "higher_lows": false,
        "range_tightening": true,
        "narrow_candle": false,
        "volume_dryup": true,
        "rs_vs_spy_1m": 0.653,
        "sma10": 60.48,
        "sma20": 73.33,
        "sma50": 61.47
      }
    },
    {
      "symbol": "ORCX",
      "stars": 2,
      "close": 26.9,
      "adr_pct": 12.21,
      "dollar_volume": 135883983.0,
      "momentum_22": 1.0291,
      "momentum_67": 2.9081,
      "momentum_126": 3.3625,
      "breakdown": {
        "ma_aligned": false,
        "higher_lows": false,
        "range_tightening": true,
        "narrow_candle": false,
        "volume_dryup": true,
        "rs_vs_spy_1m": 0.636,
        "sma10": 36.46,
        "sma20": 46.12,
        "sma50": 42.08
      }
    },
    {
      "symbol": "JBIO",
      "stars": 1,
      "close": 21.9,
      "adr_pct": 9.59,
      "dollar_volume": 27768421.0,
      "momentum_22": 1.5336,
      "momentum_67": 1.6964,
      "momentum_126": 1.759,
      "breakdown": {
        "ma_aligned": false,
        "higher_lows": true,
        "range_tightening": false,
        "narrow_candle": false,
        "volume_dryup": false,
        "rs_vs_spy_1m": 1.033,
        "sma10": 17.53,
        "sma20": 17.88,
        "sma50": 21.39
      }
    },
    {
      "symbol": "GLWG",
      "stars": 1,
      "close": 30.38,
      "adr_pct": 13.4,
      "dollar_volume": 41071066.0,
      "momentum_22": 1.4936,
      "momentum_67": 2.2222,
      "momentum_126": NaN,
      "breakdown": {
        "ma_aligned": false,
        "higher_lows": true,
        "range_tightening": false,
        "narrow_candle": false,
        "volume_dryup": false,
        "rs_vs_spy_1m": 1.035,
        "sma10": 25.72,
        "sma20": 26.3,
        "sma50": 25.97
      }
    },
    {
      "symbol": "BWIN",
      "stars": 1,
      "close": 24.87,
      "adr_pct": 6.46,
      "dollar_volume": 44028055.0,
      "momentum_22": 1.4768,
      "momentum_67": 1.4768,
      "momentum_126": 1.5661,
      "breakdown": {
        "ma_aligned": false,
        "higher_lows": false,
        "range_tightening": false,
        "narrow_candle": false,
        "volume_dryup": false,
        "rs_vs_spy_1m": 1.339,
        "sma10": 20.32,
        "sma20": 19.9,
        "sma50": 21.23
      }
    },
    {
      "symbol": "KYMR",
      "stars": 1,
      "close": 99.87,
      "adr_pct": 5.16,
      "dollar_volume": 73343332.0,
      "momentum_22": 1.4374,
      "momentum_67": 1.4374,
      "momentum_126": 1.5085,
      "breakdown": {
        "ma_aligned": false,
        "higher_lows": true,
        "range_tightening": false,
        "narrow_candle": false,
        "volume_dryup": false,
        "rs_vs_spy_1m": 1.266,
        "sma10": 89.83,
        "sma20": 83.27,
        "sma50": 83.8
      }
    },
    {
      "symbol": "FCEL",
      "stars": 1,
      "close": 21.56,
      "adr_pct": 15.46,
      "dollar_volume": 227676176.0,
      "momentum_22": 1.4316,
      "momentum_67": 3.4915,
      "momentum_126": 3.4915,
      "breakdown": {
        "ma_aligned": false,
        "higher_lows": true,
        "range_tightening": false,
        "narrow_candle": false,
        "volume_dryup": false,
        "rs_vs_spy_1m": 0.905,
        "sma10": 19.99,
        "sma20": 20.46,
        "sma50": 16.9
      }
    },
    {
      "symbol": "VSH",
      "stars": 1,
      "close": 55.59,
      "adr_pct": 10.11,
      "dollar_volume": 539165185.0,
      "momentum_22": 1.2865,
      "momentum_67": 3.4094,
      "momentum_126": 3.8364,
      "breakdown": {
        "ma_aligned": false,
        "higher_lows": false,
        "range_tightening": true,
        "narrow_candle": false,
        "volume_dryup": false,
        "rs_vs_spy_1m": 1.13,
        "sma10": 60.08,
        "sma20": 58.66,
        "sma50": 42.96
      }
    },
    {
      "symbol": "CRWG",
      "stars": 1,
      "close": 33.05,
      "adr_pct": 15.57,
      "dollar_volume": 69001149.0,
      "momentum_22": 1.1949,
      "momentum_67": 18.4123,
      "momentum_126": 18.4123,
      "breakdown": {
        "ma_aligned": false,
        "higher_lows": true,
        "range_tightening": false,
        "narrow_candle": false,
        "volume_dryup": false,
        "rs_vs_spy_1m": 0.867,
        "sma10": 37.69,
        "sma20": 39.03,
        "sma50": 30.81
      }
    },
    {
      "symbol": "IONL",
      "stars": 1,
      "close": 27.82,
      "adr_pct": 18.3,
      "dollar_volume": 28197883.0,
      "momentum_22": 1.053,
      "momentum_67": 3.1758,
      "momentum_126": 3.1758,
      "breakdown": {
        "ma_aligned": false,
        "higher_lows": false,
        "range_tightening": true,
        "narrow_candle": false,
        "volume_dryup": false,
        "rs_vs_spy_1m": 0.659,
        "sma10": 32.11,
        "sma20": 38.83,
        "sma50": 32.37
      }
    },
    {
      "symbol": "AXTI",
      "stars": 1,
      "close": 70.14,
      "adr_pct": 14.71,
      "dollar_volume": 932212751.0,
      "momentum_22": 1.0467,
      "momentum_67": 1.7668,
      "momentum_126": 5.0643,
      "breakdown": {
        "ma_aligned": false,
        "higher_lows": false,
        "range_tightening": true,
        "narrow_candle": false,
        "volume_dryup": false,
        "rs_vs_spy_1m": 0.541,
        "sma10": 89.18,
        "sma20": 96.23,
        "sma50": 97.34
      }
    }
  ]
}