{
  "generated_at": "2026-06-09T23:00:48.101293+00:00",
  "count": 81,
  "candidates": [
    {
      "symbol": "INHD",
      "close": 39.49,
      "momentum_22": 39.099,
      "momentum_67": 533.6486,
      "momentum_126": 630.8307,
      "adr_pct": 14.95,
      "dollar_volume": 550862184.0
    },
    {
      "symbol": "ASTC",
      "close": 25.58,
      "momentum_22": 11.4196,
      "momentum_67": 13.3577,
      "momentum_126": 13.3577,
      "adr_pct": 27.56,
      "dollar_volume": 306503618.0
    },
    {
      "symbol": "STI",
      "close": 20.47,
      "momentum_22": 4.6835,
      "momentum_67": 5.6782,
      "momentum_126": 6.9626,
      "adr_pct": 15.92,
      "dollar_volume": 206819507.0
    },
    {
      "symbol": "DLLL",
      "close": 159.22,
      "momentum_22": 2.507,
      "momentum_67": 6.3359,
      "momentum_126": 9.1822,
      "adr_pct": 12.39,
      "dollar_volume": 89863252.0
    },
    {
      "symbol": "MRVU",
      "close": 198.22,
      "momentum_22": 2.4535,
      "momentum_67": 9.5298,
      "momentum_126": NaN,
      "adr_pct": 18.31,
      "dollar_volume": 98901709.0
    },
    {
      "symbol": "MVLL",
      "close": 149.16,
      "momentum_22": 2.4255,
      "momentum_67": 9.3222,
      "momentum_126": 10.3043,
      "adr_pct": 18.53,
      "dollar_volume": 454161037.0
    },
    {
      "symbol": "ARMG",
      "close": 35.53,
      "momentum_22": 2.3012,
      "momentum_67": 6.3788,
      "momentum_126": 7.6656,
      "adr_pct": 17.68,
      "dollar_volume": 92876741.0
    },
    {
      "symbol": "SWMR",
      "close": 60.32,
      "momentum_22": 2.2848,
      "momentum_67": NaN,
      "momentum_126": NaN,
      "adr_pct": 15.48,
      "dollar_volume": 42257760.0
    },
    {
      "symbol": "OCC",
      "close": 21.01,
      "momentum_22": 2.1863,
      "momentum_67": 3.7186,
      "momentum_126": 5.2264,
      "adr_pct": 13.38,
      "dollar_volume": 25165632.0
    },
    {
      "symbol": "AMBQ",
      "close": 76.04,
      "momentum_22": 1.9802,
      "momentum_67": 3.3424,
      "momentum_126": 3.3424,
      "adr_pct": 9.25,
      "dollar_volume": 70138158.0
    },
    {
      "symbol": "AGL",
      "close": 102.16,
      "momentum_22": 1.9797,
      "momentum_67": 336.0526,
      "momentum_126": 336.0526,
      "adr_pct": 10.61,
      "dollar_volume": 27863251.0
    },
    {
      "symbol": "VPG",
      "close": 122.66,
      "momentum_22": 1.9332,
      "momentum_67": 3.1323,
      "momentum_126": 3.3735,
      "adr_pct": 9.84,
      "dollar_volume": 84756277.0
    },
    {
      "symbol": "MUU",
      "close": 767.43,
      "momentum_22": 1.8954,
      "momentum_67": 7.4893,
      "momentum_126": 12.3394,
      "adr_pct": 13.96,
      "dollar_volume": 2515242402.0
    },
    {
      "symbol": "MULL",
      "close": 669.21,
      "momentum_22": 1.8876,
      "momentum_67": 7.391,
      "momentum_126": 11.9995,
      "adr_pct": 13.87,
      "dollar_volume": 285249891.0
    },
    {
      "symbol": "UMAC",
      "close": 23.9,
      "momentum_22": 1.8463,
      "momentum_67": 2.2462,
      "momentum_126": 2.7598,
      "adr_pct": 14.29,
      "dollar_volume": 252314098.0
    },
    {
      "symbol": "VSH",
      "close": 58.58,
      "momentum_22": 1.808,
      "momentum_67": 3.7527,
      "momentum_126": 4.0624,
      "adr_pct": 9.18,
      "dollar_volume": 455083900.0
    },
    {
      "symbol": "ALAB",
      "close": 341.7,
      "momentum_22": 1.8014,
      "momentum_67": 3.4907,
      "momentum_126": 3.4907,
      "adr_pct": 9.73,
      "dollar_volume": 1875094960.0
    },
    {
      "symbol": "BRUN",
      "close": 29.15,
      "momentum_22": 1.7774,
      "momentum_67": 2.7474,
      "momentum_126": 2.7526,
      "adr_pct": 16.51,
      "dollar_volume": 73085917.0
    },
    {
      "symbol": "SMCX",
      "close": 21.81,
      "momentum_22": 1.7546,
      "momentum_67": 3.3657,
      "momentum_126": 3.3657,
      "adr_pct": 14.57,
      "dollar_volume": 57633844.0
    },
    {
      "symbol": "HIMZ",
      "close": 36.52,
      "momentum_22": 1.7474,
      "momentum_67": 35.1154,
      "momentum_126": 41.2935,
      "adr_pct": 14.48,
      "dollar_volume": 24075845.0
    },
    {
      "symbol": "RXO",
      "close": 29.12,
      "momentum_22": 1.7385,
      "momentum_67": 2.4932,
      "momentum_126": 2.6047,
      "adr_pct": 6.83,
      "dollar_volume": 64289897.0
    },
    {
      "symbol": "VSXY",
      "close": 74.96,
      "momentum_22": 1.7384,
      "momentum_67": 1.7852,
      "momentum_126": 1.7852,
      "adr_pct": 6.35,
      "dollar_volume": 206043874.0
    },
    {
      "symbol": "AEVA",
      "close": 22.17,
      "momentum_22": 1.7381,
      "momentum_67": 1.9345,
      "momentum_126": 1.9821,
      "adr_pct": 12.17,
      "dollar_volume": 69583548.0
    },
    {
      "symbol": "MRVL",
      "close": 266.88,
      "momentum_22": 1.6895,
      "momentum_67": 3.547,
      "momentum_126": 3.7756,
      "adr_pct": 9.34,
      "dollar_volume": 12793679430.0
    },
    {
      "symbol": "DELL",
      "close": 381.78,
      "momentum_22": 1.6799,
      "momentum_67": 2.7767,
      "momentum_126": 3.4638,
      "adr_pct": 6.49,
      "dollar_volume": 4305165523.0
    },
    {
      "symbol": "SNOW",
      "close": 239.66,
      "momentum_22": 1.6588,
      "momentum_67": 2.0259,
      "momentum_126": 2.0259,
      "adr_pct": 5.35,
      "dollar_volume": 2447349567.0
    },
    {
      "symbol": "MEC",
      "close": 34.74,
      "momentum_22": 1.6543,
      "momentum_67": 2.1055,
      "momentum_126": 2.1055,
      "adr_pct": 7.09,
      "dollar_volume": 20345180.0
    },
    {
      "symbol": "HPE",
      "close": 48.27,
      "momentum_22": 1.6368,
      "momentum_67": 2.3432,
      "momentum_126": 2.433,
      "adr_pct": 6.08,
      "dollar_volume": 1774369433.0
    },
    {
      "symbol": "OUST",
      "close": 38.52,
      "momentum_22": 1.6322,
      "momentum_67": 2.3488,
      "momentum_126": 2.3488,
      "adr_pct": 12.48,
      "dollar_volume": 224656836.0
    },
    {
      "symbol": "TNGX",
      "close": 31.56,
      "momentum_22": 1.6317,
      "momentum_67": 2.6746,
      "momentum_126": 3.8024,
      "adr_pct": 8.95,
      "dollar_volume": 103104151.0
    },
    {
      "symbol": "ARM",
      "close": 324.86,
      "momentum_22": 1.6171,
      "momentum_67": 2.9198,
      "momentum_126": 3.248,
      "adr_pct": 9.06,
      "dollar_volume": 3943458773.0
    },
    {
      "symbol": "LQDA",
      "close": 64.01,
      "momentum_22": 1.6164,
      "momentum_67": 2.0129,
      "momentum_126": 2.1985,
      "adr_pct": 6.37,
      "dollar_volume": 112549351.0
    },
    {
      "symbol": "ARCB",
      "close": 173.22,
      "momentum_22": 1.5753,
      "momentum_67": 2.0935,
      "momentum_126": 2.5197,
      "adr_pct": 4.34,
      "dollar_volume": 47370900.0
    },
    {
      "symbol": "CRDO",
      "close": 234.32,
      "momentum_22": 1.5732,
      "momentum_67": 2.7094,
      "momentum_126": 2.7094,
      "adr_pct": 10.51,
      "dollar_volume": 1846904636.0
    },
    {
      "symbol": "NSIT",
      "close": 109.8,
      "momentum_22": 1.5715,
      "momentum_67": 1.7259,
      "momentum_126": 1.7259,
      "adr_pct": 5.27,
      "dollar_volume": 55252559.0
    },
    {
      "symbol": "PENG",
      "close": 61.69,
      "momentum_22": 1.5564,
      "momentum_67": 3.846,
      "momentum_126": 3.846,
      "adr_pct": 10.53,
      "dollar_volume": 209511490.0
    },
    {
      "symbol": "OKTA",
      "close": 119.96,
      "momentum_22": 1.5489,
      "momentum_67": 1.9145,
      "momentum_126": 1.9145,
      "adr_pct": 5.69,
      "dollar_volume": 548380947.0
    },
    {
      "symbol": "TXG",
      "close": 30.59,
      "momentum_22": 1.5434,
      "momentum_67": 1.9239,
      "momentum_126": 2.0152,
      "adr_pct": 7.32,
      "dollar_volume": 82461039.0
    },
    {
      "symbol": "HAE",
      "close": 78.71,
      "momentum_22": 1.5433,
      "momentum_67": 1.5433,
      "momentum_126": 1.5433,
      "adr_pct": 4.38,
      "dollar_volume": 65778985.0
    },
    {
      "symbol": "CORT",
      "close": 77.49,
      "momentum_22": 1.5399,
      "momentum_67": 2.436,
      "momentum_126": 2.7038,
      "adr_pct": 4.14,
      "dollar_volume": 69327553.0
    },
    {
      "symbol": "VOYG",
      "close": 39.47,
      "momentum_22": 1.5239,
      "momentum_67": 1.8206,
      "momentum_126": 1.8206,
      "adr_pct": 10.96,
      "dollar_volume": 122040178.0
    },
    {
      "symbol": "ENPH",
      "close": 53.51,
      "momentum_22": 1.5197,
      "momentum_67": 1.7896,
      "momentum_126": 1.7896,
      "adr_pct": 11.01,
      "dollar_volume": 600443310.0
    },
    {
      "symbol": "SEDG",
      "close": 57.8,
      "momentum_22": 1.5009,
      "momentum_67": 1.8349,
      "momentum_126": 2.0489,
      "adr_pct": 11.37,
      "dollar_volume": 303004537.0
    },
    {
      "symbol": "WGS",
      "close": 56.33,
      "momentum_22": 1.4993,
      "momentum_67": 1.7488,
      "momentum_126": 1.7488,
      "adr_pct": 7.5,
      "dollar_volume": 62059627.0
    },
    {
      "symbol": "ALNT",
      "close": 86.92,
      "momentum_22": 1.482,
      "momentum_67": 1.5766,
      "momentum_126": 1.7043,
      "adr_pct": 5.77,
      "dollar_volume": 20327502.0
    },
    {
      "symbol": "NBIL",
      "close": 38.06,
      "momentum_22": 1.4758,
      "momentum_67": 4.8858,
      "momentum_126": 5.9749,
      "adr_pct": 19.32,
      "dollar_volume": 62705806.0
    },
    {
      "symbol": "ABVX",
      "close": 102.72,
      "momentum_22": 1.4714,
      "momentum_67": 1.4714,
      "momentum_126": 1.4714,
      "adr_pct": 6.59,
      "dollar_volume": 288746893.0
    },
    {
      "symbol": "NBIG",
      "close": 26.49,
      "momentum_22": 1.466,
      "momentum_67": 4.8164,
      "momentum_126": 5.8736,
      "adr_pct": 19.22,
      "dollar_volume": 32006842.0
    },
    {
      "symbol": "NTAP",
      "close": 165.0,
      "momentum_22": 1.4654,
      "momentum_67": 1.7389,
      "momentum_126": 1.7611,
      "adr_pct": 5.06,
      "dollar_volume": 661176993.0
    },
    {
      "symbol": "NVTS",
      "close": 22.85,
      "momentum_22": 1.4647,
      "momentum_67": 2.983,
      "momentum_126": 3.216,
      "adr_pct": 12.57,
      "dollar_volume": 1007518812.0
    },
    {
      "symbol": "MU",
      "close": 935.89,
      "momentum_22": 1.435,
      "momentum_67": 3.0046,
      "momentum_126": 4.2216,
      "adr_pct": 6.96,
      "dollar_volume": 48695312180.0
    },
    {
      "symbol": "IONL",
      "close": 31.9,
      "momentum_22": 1.4124,
      "momentum_67": 3.6416,
      "momentum_126": 3.6416,
      "adr_pct": 19.17,
      "dollar_volume": 40192258.0
    },
    {
      "symbol": "IONX",
      "close": 60.57,
      "momentum_22": 1.4119,
      "momentum_67": 6.695,
      "momentum_126": 7.2107,
      "adr_pct": 19.22,
      "dollar_volume": 140425992.0
    },
    {
      "symbol": "AMUU",
      "close": 203.32,
      "momentum_22": 1.409,
      "momentum_67": 5.3519,
      "momentum_126": 5.3576,
      "adr_pct": 11.26,
      "dollar_volume": 31072182.0
    },
    {
      "symbol": "AMDL",
      "close": 57.89,
      "momentum_22": 1.4061,
      "momentum_67": 5.3404,
      "momentum_126": 5.3602,
      "adr_pct": 11.8,
      "dollar_volume": 384262456.0
    },
    {
      "symbol": "INOD",
      "close": 98.77,
      "momentum_22": 1.3567,
      "momentum_67": 2.8855,
      "momentum_126": 2.8855,
      "adr_pct": 11.45,
      "dollar_volume": 212811625.0
    },
    {
      "symbol": "BAND",
      "close": 63.36,
      "momentum_22": 1.3536,
      "momentum_67": 4.2753,
      "momentum_126": 5.0688,
      "adr_pct": 8.18,
      "dollar_volume": 69304772.0
    },
    {
      "symbol": "RGTX",
      "close": 20.4,
      "momentum_22": 1.3456,
      "momentum_67": 4.3129,
      "momentum_126": 4.4493,
      "adr_pct": 23.14,
      "dollar_volume": 109969599.0
    },
    {
      "symbol": "SHAZ",
      "close": 63.42,
      "momentum_22": 1.3349,
      "momentum_67": 3.7427,
      "momentum_126": NaN,
      "adr_pct": 12.27,
      "dollar_volume": 44235374.0
    },
    {
      "symbol": "RKLX",
      "close": 55.6,
      "momentum_22": 1.3295,
      "momentum_67": 2.8081,
      "momentum_126": 2.8081,
      "adr_pct": 16.64,
      "dollar_volume": 287482629.0
    },
    {
      "symbol": "APPX",
      "close": 42.4,
      "momentum_22": 1.299,
      "momentum_67": 2.9933,
      "momentum_126": 5.2281,
      "adr_pct": 12.7,
      "dollar_volume": 29919775.0
    },
    {
      "symbol": "HUT",
      "close": 112.65,
      "momentum_22": 1.2975,
      "momentum_67": 2.6783,
      "momentum_126": 3.2958,
      "adr_pct": 8.29,
      "dollar_volume": 497657639.0
    },
    {
      "symbol": "SNDK",
      "close": 1646.54,
      "momentum_22": 1.289,
      "momentum_67": 3.1848,
      "momentum_126": 8.2533,
      "adr_pct": 7.89,
      "dollar_volume": 18114606313.0
    },
    {
      "symbol": "UCTT",
      "close": 91.88,
      "momentum_22": 1.271,
      "momentum_67": 1.8863,
      "momentum_126": 3.8572,
      "adr_pct": 7.41,
      "dollar_volume": 95510007.0
    },
    {
      "symbol": "ORCX",
      "close": 47.17,
      "momentum_22": 1.2629,
      "momentum_67": 5.2093,
      "momentum_126": 5.8963,
      "adr_pct": 11.16,
      "dollar_volume": 106972643.0
    },
    {
      "symbol": "ATEX",
      "close": 64.55,
      "momentum_22": 1.247,
      "momentum_67": 1.8573,
      "momentum_126": 3.2003,
      "adr_pct": 6.57,
      "dollar_volume": 22854345.0
    },
    {
      "symbol": "AEHR",
      "close": 94.31,
      "momentum_22": 1.2286,
      "momentum_67": 3.2376,
      "momentum_126": 4.7392,
      "adr_pct": 12.16,
      "dollar_volume": 234875563.0
    },
    {
      "symbol": "DOCN",
      "close": 168.33,
      "momentum_22": 1.2092,
      "momentum_67": 3.2427,
      "momentum_126": 3.8423,
      "adr_pct": 7.73,
      "dollar_volume": 503795222.0
    },
    {
      "symbol": "LINT",
      "close": 162.13,
      "momentum_22": 1.1955,
      "momentum_67": 5.8488,
      "momentum_126": 6.3806,
      "adr_pct": 13.84,
      "dollar_volume": 40359211.0
    },
    {
      "symbol": "WDC",
      "close": 517.72,
      "momentum_22": 1.1929,
      "momentum_67": 2.1753,
      "momentum_126": 3.1288,
      "adr_pct": 5.97,
      "dollar_volume": 3396167015.0
    },
    {
      "symbol": "INTW",
      "close": 254.77,
      "momentum_22": 1.1916,
      "momentum_67": 5.7902,
      "momentum_126": 6.5747,
      "adr_pct": 14.24,
      "dollar_volume": 247966284.0
    },
    {
      "symbol": "ICHR",
      "close": 71.6,
      "momentum_22": 1.1517,
      "momentum_67": 1.8636,
      "momentum_126": 4.312,
      "adr_pct": 7.05,
      "dollar_volume": 75735884.0
    },
    {
      "symbol": "SOLT",
      "close": 26.44,
      "momentum_22": 1.1357,
      "momentum_67": 1.1357,
      "momentum_126": 12.8976,
      "adr_pct": 7.1,
      "dollar_volume": 20555544.0
    },
    {
      "symbol": "AAOI",
      "close": 162.88,
      "momentum_22": 1.1344,
      "momentum_67": 2.0729,
      "momentum_126": 6.0776,
      "adr_pct": 13.91,
      "dollar_volume": 2447338187.0
    },
    {
      "symbol": "QURE",
      "close": 26.46,
      "momentum_22": 1.1264,
      "momentum_67": 2.9498,
      "momentum_126": 3.0309,
      "adr_pct": 6.88,
      "dollar_volume": 43743697.0
    },
    {
      "symbol": "CRWG",
      "close": 32.34,
      "momentum_22": 1.1098,
      "momentum_67": 18.0167,
      "momentum_126": 18.0167,
      "adr_pct": 14.27,
      "dollar_volume": 58800279.0
    },
    {
      "symbol": "MRAM",
      "close": 23.28,
      "momentum_22": 1.0955,
      "momentum_67": 2.91,
      "momentum_126": 2.91,
      "adr_pct": 15.91,
      "dollar_volume": 186932861.0
    },
    {
      "symbol": "WOLF",
      "close": 48.78,
      "momentum_22": 1.0811,
      "momentum_67": 3.3457,
      "momentum_126": 3.6174,
      "adr_pct": 17.43,
      "dollar_volume": 683584007.0
    },
    {
      "symbol": "BE",
      "close": 259.61,
      "momentum_22": 1.0739,
      "momentum_67": 2.2283,
      "momentum_126": 3.4295,
      "adr_pct": 8.4,
      "dollar_volume": 2866861087.0
    },
    {
      "symbol": "MXL",
      "close": 72.61,
      "momentum_22": 1.0714,
      "momentum_67": 4.9395,
      "momentum_126": 4.9395,
      "adr_pct": 13.16,
      "dollar_volume": 467155555.0
    },
    {
      "symbol": "AXTI",
      "close": 78.36,
      "momentum_22": 1.0311,
      "momentum_67": 2.4837,
      "momentum_126": 6.6463,
      "adr_pct": 14.68,
      "dollar_volume": 967066339.0
    }
  ]
}