{
  "generated_at": "2026-07-07T22:38:56.906986+00:00",
  "count": 97,
  "candidates": [
    {
      "symbol": "INHD",
      "close": 39.49,
      "momentum_22": 37.9712,
      "momentum_67": 533.6486,
      "momentum_126": 533.6486,
      "adr_pct": 6.3,
      "dollar_volume": 550706424.0
    },
    {
      "symbol": "SDOT",
      "close": 40.0,
      "momentum_22": 8.2988,
      "momentum_67": 277.7778,
      "momentum_126": 277.7778,
      "adr_pct": 67.49,
      "dollar_volume": 129922893.0
    },
    {
      "symbol": "CRNX",
      "close": 83.53,
      "momentum_22": 2.5583,
      "momentum_67": 2.5861,
      "momentum_126": 2.5861,
      "adr_pct": 4.53,
      "dollar_volume": 394610727.0
    },
    {
      "symbol": "HQ",
      "close": 23.5,
      "momentum_22": 2.4103,
      "momentum_67": 2.8347,
      "momentum_126": NaN,
      "adr_pct": 19.83,
      "dollar_volume": 39676993.0
    },
    {
      "symbol": "MBX",
      "close": 62.0,
      "momentum_22": 2.2143,
      "momentum_67": 2.2496,
      "momentum_126": 2.3718,
      "adr_pct": 8.54,
      "dollar_volume": 51403185.0
    },
    {
      "symbol": "DFTX",
      "close": 44.48,
      "momentum_22": 2.0507,
      "momentum_67": 2.5158,
      "momentum_126": 3.4529,
      "adr_pct": 7.43,
      "dollar_volume": 185448120.0
    },
    {
      "symbol": "HOOG",
      "close": 37.61,
      "momentum_22": 1.9578,
      "momentum_67": 2.4711,
      "momentum_126": 2.6063,
      "adr_pct": 13.18,
      "dollar_volume": 23282601.0
    },
    {
      "symbol": "ABVX",
      "close": 142.17,
      "momentum_22": 1.9009,
      "momentum_67": 2.0365,
      "momentum_126": 2.0365,
      "adr_pct": 6.87,
      "dollar_volume": 291597462.0
    },
    {
      "symbol": "HIMZ",
      "close": 52.7,
      "momentum_22": 1.8761,
      "momentum_67": 2.8288,
      "momentum_126": 59.5884,
      "adr_pct": 15.6,
      "dollar_volume": 22914411.0
    },
    {
      "symbol": "MRNA",
      "close": 79.77,
      "momentum_22": 1.757,
      "momentum_67": 1.8262,
      "momentum_126": 2.551,
      "adr_pct": 8.07,
      "dollar_volume": 642336985.0
    },
    {
      "symbol": "FCEL",
      "close": 25.96,
      "momentum_22": 1.7238,
      "momentum_67": 4.1939,
      "momentum_126": 4.204,
      "adr_pct": 17.61,
      "dollar_volume": 346690210.0
    },
    {
      "symbol": "GRPN",
      "close": 26.85,
      "momentum_22": 1.7223,
      "momentum_67": 2.4954,
      "momentum_126": 2.928,
      "adr_pct": 7.89,
      "dollar_volume": 35174358.0
    },
    {
      "symbol": "NRIX",
      "close": 24.4,
      "momentum_22": 1.7135,
      "momentum_67": 1.7135,
      "momentum_126": 1.7416,
      "adr_pct": 7.64,
      "dollar_volume": 71270919.0
    },
    {
      "symbol": "RARE",
      "close": 35.87,
      "momentum_22": 1.677,
      "momentum_67": 1.8357,
      "momentum_126": 1.9612,
      "adr_pct": 5.16,
      "dollar_volume": 95977364.0
    },
    {
      "symbol": "ALHC",
      "close": 24.05,
      "momentum_22": 1.6512,
      "momentum_67": 1.8429,
      "momentum_126": 1.8429,
      "adr_pct": 5.55,
      "dollar_volume": 128878483.0
    },
    {
      "symbol": "ZBIO",
      "close": 27.68,
      "momentum_22": 1.6506,
      "momentum_67": 1.6868,
      "momentum_126": 2.0504,
      "adr_pct": 7.46,
      "dollar_volume": 25600772.0
    },
    {
      "symbol": "GSHD",
      "close": 55.6,
      "momentum_22": 1.6421,
      "momentum_67": 1.6508,
      "momentum_126": 1.6508,
      "adr_pct": 5.83,
      "dollar_volume": 24920404.0
    },
    {
      "symbol": "KYMR",
      "close": 119.24,
      "momentum_22": 1.6411,
      "momentum_67": 1.7162,
      "momentum_126": 1.8011,
      "adr_pct": 6.63,
      "dollar_volume": 134934149.0
    },
    {
      "symbol": "ATEX",
      "close": 100.9,
      "momentum_22": 1.6405,
      "momentum_67": 2.9032,
      "momentum_126": 4.6052,
      "adr_pct": 9.05,
      "dollar_volume": 56130305.0
    },
    {
      "symbol": "AGIO",
      "close": 44.01,
      "momentum_22": 1.6367,
      "momentum_67": 1.8119,
      "momentum_126": 1.8119,
      "adr_pct": 4.73,
      "dollar_volume": 46239354.0
    },
    {
      "symbol": "SMST",
      "close": 60.4,
      "momentum_22": 1.6284,
      "momentum_67": 2.786,
      "momentum_126": 2.786,
      "adr_pct": 16.05,
      "dollar_volume": 23475902.0
    },
    {
      "symbol": "BWIN",
      "close": 27.3,
      "momentum_22": 1.6211,
      "momentum_67": 1.6211,
      "momentum_126": 1.7191,
      "adr_pct": 6.36,
      "dollar_volume": 50636366.0
    },
    {
      "symbol": "PTRN",
      "close": 28.3,
      "momentum_22": 1.6171,
      "momentum_67": 2.4673,
      "momentum_126": 3.1726,
      "adr_pct": 5.82,
      "dollar_volume": 63297986.0
    },
    {
      "symbol": "QURE",
      "close": 41.41,
      "momentum_22": 1.6144,
      "momentum_67": 3.1347,
      "momentum_126": 4.7434,
      "adr_pct": 6.89,
      "dollar_volume": 134413924.0
    },
    {
      "symbol": "DMRA",
      "close": 30.0,
      "momentum_22": 1.6138,
      "momentum_67": 1.6138,
      "momentum_126": 1.8182,
      "adr_pct": 9.85,
      "dollar_volume": 23176835.0
    },
    {
      "symbol": "VOR",
      "close": 20.1,
      "momentum_22": 1.5978,
      "momentum_67": 1.5978,
      "momentum_126": 1.9534,
      "adr_pct": 7.84,
      "dollar_volume": 29037907.0
    },
    {
      "symbol": "ALMS",
      "close": 29.27,
      "momentum_22": 1.5942,
      "momentum_67": 1.5942,
      "momentum_126": 3.7287,
      "adr_pct": 6.95,
      "dollar_volume": 45403726.0
    },
    {
      "symbol": "AXON",
      "close": 640.46,
      "momentum_22": 1.5932,
      "momentum_67": 1.8892,
      "momentum_126": 1.8892,
      "adr_pct": 6.29,
      "dollar_volume": 590794403.0
    },
    {
      "symbol": "TENB",
      "close": 40.62,
      "momentum_22": 1.5927,
      "momentum_67": 2.5831,
      "momentum_126": 2.5831,
      "adr_pct": 6.1,
      "dollar_volume": 108617047.0
    },
    {
      "symbol": "PLTU",
      "close": 33.16,
      "momentum_22": 1.576,
      "momentum_67": 1.576,
      "momentum_126": 1.576,
      "adr_pct": 9.26,
      "dollar_volume": 98240725.0
    },
    {
      "symbol": "JBIO",
      "close": 22.45,
      "momentum_22": 1.5721,
      "momentum_67": 1.6617,
      "momentum_126": 1.8032,
      "adr_pct": 8.33,
      "dollar_volume": 27027008.0
    },
    {
      "symbol": "SEZL",
      "close": 177.63,
      "momentum_22": 1.5674,
      "momentum_67": 3.1323,
      "momentum_126": 3.2296,
      "adr_pct": 6.67,
      "dollar_volume": 107553480.0
    },
    {
      "symbol": "DAVE",
      "close": 383.96,
      "momentum_22": 1.5608,
      "momentum_67": 2.3412,
      "momentum_126": 2.5226,
      "adr_pct": 8.04,
      "dollar_volume": 215101217.0
    },
    {
      "symbol": "GPCR",
      "close": 56.63,
      "momentum_22": 1.5538,
      "momentum_67": 1.5827,
      "momentum_126": 1.5827,
      "adr_pct": 5.39,
      "dollar_volume": 45230089.0
    },
    {
      "symbol": "VKTX",
      "close": 42.13,
      "momentum_22": 1.5512,
      "momentum_67": 1.5512,
      "momentum_126": 1.6348,
      "adr_pct": 6.1,
      "dollar_volume": 105003685.0
    },
    {
      "symbol": "TNGX",
      "close": 30.12,
      "momentum_22": 1.5504,
      "momentum_67": 1.5655,
      "momentum_126": 3.4781,
      "adr_pct": 7.69,
      "dollar_volume": 204631730.0
    },
    {
      "symbol": "QNT",
      "close": 77.6,
      "momentum_22": 1.5489,
      "momentum_67": NaN,
      "momentum_126": NaN,
      "adr_pct": 12.62,
      "dollar_volume": 270850149.0
    },
    {
      "symbol": "BCAX",
      "close": 30.4,
      "momentum_22": 1.5455,
      "momentum_67": 1.6327,
      "momentum_126": 2.2109,
      "adr_pct": 5.7,
      "dollar_volume": 27735617.0
    },
    {
      "symbol": "LMND",
      "close": 77.59,
      "momentum_22": 1.5441,
      "momentum_67": 1.5441,
      "momentum_126": 1.6068,
      "adr_pct": 6.66,
      "dollar_volume": 102072375.0
    },
    {
      "symbol": "ELF",
      "close": 75.34,
      "momentum_22": 1.5432,
      "momentum_67": 1.5432,
      "momentum_126": 1.5432,
      "adr_pct": 6.53,
      "dollar_volume": 257147555.0
    },
    {
      "symbol": "HNGE",
      "close": 89.3,
      "momentum_22": 1.5356,
      "momentum_67": 2.5779,
      "momentum_126": 2.9688,
      "adr_pct": 5.46,
      "dollar_volume": 181392474.0
    },
    {
      "symbol": "MMYT",
      "close": 58.7,
      "momentum_22": 1.5342,
      "momentum_67": 1.6948,
      "momentum_126": 1.7968,
      "adr_pct": 5.99,
      "dollar_volume": 67710890.0
    },
    {
      "symbol": "WYFI",
      "close": 33.42,
      "momentum_22": 1.534,
      "momentum_67": 3.0802,
      "momentum_126": 3.1798,
      "adr_pct": 15.29,
      "dollar_volume": 99998613.0
    },
    {
      "symbol": "CBRL",
      "close": 49.5,
      "momentum_22": 1.5299,
      "momentum_67": 1.8212,
      "momentum_126": 1.8872,
      "adr_pct": 6.27,
      "dollar_volume": 86691459.0
    },
    {
      "symbol": "ELVN",
      "close": 50.92,
      "momentum_22": 1.5223,
      "momentum_67": 1.5223,
      "momentum_126": 3.444,
      "adr_pct": 6.98,
      "dollar_volume": 115795047.0
    },
    {
      "symbol": "GLUE",
      "close": 24.4,
      "momentum_22": 1.5146,
      "momentum_67": 1.5312,
      "momentum_126": 1.7823,
      "adr_pct": 7.13,
      "dollar_volume": 35594889.0
    },
    {
      "symbol": "IDYA",
      "close": 40.51,
      "momentum_22": 1.511,
      "momentum_67": 1.511,
      "momentum_126": 1.511,
      "adr_pct": 5.8,
      "dollar_volume": 58450828.0
    },
    {
      "symbol": "LQDA",
      "close": 81.23,
      "momentum_22": 1.4905,
      "momentum_67": 2.2979,
      "momentum_126": 2.7899,
      "adr_pct": 5.74,
      "dollar_volume": 191354202.0
    },
    {
      "symbol": "NAVN",
      "close": 27.25,
      "momentum_22": 1.485,
      "momentum_67": 2.3675,
      "momentum_126": 3.3621,
      "adr_pct": 7.19,
      "dollar_volume": 140808427.0
    },
    {
      "symbol": "FOUR",
      "close": 51.16,
      "momentum_22": 1.4803,
      "momentum_67": 1.4803,
      "momentum_126": 1.4803,
      "adr_pct": 6.45,
      "dollar_volume": 80473436.0
    },
    {
      "symbol": "ORKA",
      "close": 84.5,
      "momentum_22": 1.4706,
      "momentum_67": 1.8342,
      "momentum_126": 3.3492,
      "adr_pct": 6.56,
      "dollar_volume": 156866926.0
    },
    {
      "symbol": "OSCR",
      "close": 31.12,
      "momentum_22": 1.4223,
      "momentum_67": 2.8446,
      "momentum_126": 2.9111,
      "adr_pct": 6.21,
      "dollar_volume": 214220780.0
    },
    {
      "symbol": "BAND",
      "close": 67.56,
      "momentum_22": 1.4031,
      "momentum_67": 4.2517,
      "momentum_126": 5.4048,
      "adr_pct": 8.78,
      "dollar_volume": 91307154.0
    },
    {
      "symbol": "ICHR",
      "close": 85.01,
      "momentum_22": 1.3615,
      "momentum_67": 1.9706,
      "momentum_126": 4.0831,
      "adr_pct": 9.28,
      "dollar_volume": 127700341.0
    },
    {
      "symbol": "AMDL",
      "close": 64.19,
      "momentum_22": 1.3304,
      "momentum_67": 5.6209,
      "momentum_126": 5.9435,
      "adr_pct": 12.26,
      "dollar_volume": 303339439.0
    },
    {
      "symbol": "SYRE",
      "close": 94.23,
      "momentum_22": 1.3292,
      "momentum_67": 2.0367,
      "momentum_126": 3.3654,
      "adr_pct": 5.97,
      "dollar_volume": 163128293.0
    },
    {
      "symbol": "AMUU",
      "close": 225.2,
      "momentum_22": 1.3123,
      "momentum_67": 5.6484,
      "momentum_126": 5.9341,
      "adr_pct": 11.36,
      "dollar_volume": 28745382.0
    },
    {
      "symbol": "CORT",
      "close": 94.04,
      "momentum_22": 1.3009,
      "momentum_67": 2.4426,
      "momentum_126": 3.2812,
      "adr_pct": 4.58,
      "dollar_volume": 86860098.0
    },
    {
      "symbol": "AGL",
      "close": 107.47,
      "momentum_22": 1.2902,
      "momentum_67": 14.3676,
      "momentum_126": 353.5197,
      "adr_pct": 9.2,
      "dollar_volume": 35507664.0
    },
    {
      "symbol": "CDNL",
      "close": 75.85,
      "momentum_22": 1.2856,
      "momentum_67": 2.0461,
      "momentum_126": 3.4509,
      "adr_pct": 9.14,
      "dollar_volume": 72789928.0
    },
    {
      "symbol": "ACMR",
      "close": 94.66,
      "momentum_22": 1.2759,
      "momentum_67": 2.5474,
      "momentum_126": 2.5474,
      "adr_pct": 9.68,
      "dollar_volume": 197525303.0
    },
    {
      "symbol": "UMC",
      "close": 23.83,
      "momentum_22": 1.2747,
      "momentum_67": 2.8745,
      "momentum_126": 3.0968,
      "adr_pct": 5.42,
      "dollar_volume": 476293878.0
    },
    {
      "symbol": "SHAZ",
      "close": 71.76,
      "momentum_22": 1.2672,
      "momentum_67": 3.3801,
      "momentum_126": NaN,
      "adr_pct": 14.0,
      "dollar_volume": 131168274.0
    },
    {
      "symbol": "MXL",
      "close": 85.82,
      "momentum_22": 1.2663,
      "momentum_67": 5.2926,
      "momentum_126": 5.8381,
      "adr_pct": 11.36,
      "dollar_volume": 363712017.0
    },
    {
      "symbol": "ALAB",
      "close": 382.89,
      "momentum_22": 1.2637,
      "momentum_67": 3.8251,
      "momentum_126": 3.9114,
      "adr_pct": 10.14,
      "dollar_volume": 2647824970.0
    },
    {
      "symbol": "OUST",
      "close": 44.06,
      "momentum_22": 1.2482,
      "momentum_67": 2.5976,
      "momentum_126": 2.6866,
      "adr_pct": 13.34,
      "dollar_volume": 258692672.0
    },
    {
      "symbol": "SIMO",
      "close": 294.9,
      "momentum_22": 1.2331,
      "momentum_67": 2.7923,
      "momentum_126": 3.1662,
      "adr_pct": 7.89,
      "dollar_volume": 263628560.0
    },
    {
      "symbol": "CRDO",
      "close": 246.4,
      "momentum_22": 1.232,
      "momentum_67": 2.7968,
      "momentum_126": 2.849,
      "adr_pct": 10.36,
      "dollar_volume": 2735158778.0
    },
    {
      "symbol": "XMTR",
      "close": 93.1,
      "momentum_22": 1.2119,
      "momentum_67": 2.5326,
      "momentum_126": 2.5962,
      "adr_pct": 5.3,
      "dollar_volume": 68911378.0
    },
    {
      "symbol": "DDOG",
      "close": 256.81,
      "momentum_22": 1.2072,
      "momentum_67": 2.5478,
      "momentum_126": 2.6202,
      "adr_pct": 5.02,
      "dollar_volume": 1142902190.0
    },
    {
      "symbol": "AMD",
      "close": 516.11,
      "momentum_22": 1.1804,
      "momentum_67": 2.6277,
      "momentum_126": 2.7421,
      "adr_pct": 6.17,
      "dollar_volume": 16334900458.0
    },
    {
      "symbol": "DELL",
      "close": 417.28,
      "momentum_22": 1.1686,
      "momentum_67": 2.6857,
      "momentum_126": 3.7859,
      "adr_pct": 7.28,
      "dollar_volume": 3354754728.0
    },
    {
      "symbol": "LINT",
      "close": 156.77,
      "momentum_22": 1.156,
      "momentum_67": 5.3725,
      "momentum_126": 5.6555,
      "adr_pct": 14.49,
      "dollar_volume": 37331073.0
    },
    {
      "symbol": "INTC",
      "close": 110.39,
      "momentum_22": 1.1226,
      "momentum_67": 2.6536,
      "momentum_126": 2.8341,
      "adr_pct": 7.54,
      "dollar_volume": 16387625926.0
    },
    {
      "symbol": "MUU",
      "close": 688.61,
      "momentum_22": 1.1177,
      "momentum_67": 6.7201,
      "momentum_126": 6.7201,
      "adr_pct": 14.76,
      "dollar_volume": 3151552046.0
    },
    {
      "symbol": "UCTT",
      "close": 90.78,
      "momentum_22": 1.1118,
      "momentum_67": 1.5974,
      "momentum_126": 3.226,
      "adr_pct": 9.21,
      "dollar_volume": 176670981.0
    },
    {
      "symbol": "CRWG",
      "close": 21.72,
      "momentum_22": 1.1099,
      "momentum_67": 10.3918,
      "momentum_126": 12.1003,
      "adr_pct": 14.75,
      "dollar_volume": 51875227.0
    },
    {
      "symbol": "PENG",
      "close": 62.71,
      "momentum_22": 1.1078,
      "momentum_67": 3.8191,
      "momentum_126": 3.9096,
      "adr_pct": 11.29,
      "dollar_volume": 219255054.0
    },
    {
      "symbol": "WDC",
      "close": 532.1,
      "momentum_22": 1.1065,
      "momentum_67": 2.0908,
      "momentum_126": 2.9447,
      "adr_pct": 8.02,
      "dollar_volume": 6765937459.0
    },
    {
      "symbol": "MU",
      "close": 938.38,
      "momentum_22": 1.0984,
      "momentum_67": 3.0126,
      "momentum_126": 3.0314,
      "adr_pct": 7.64,
      "dollar_volume": 60217047481.0
    },
    {
      "symbol": "AXTI",
      "close": 58.15,
      "momentum_22": 1.0898,
      "momentum_67": 1.4647,
      "momentum_126": 3.9774,
      "adr_pct": 13.67,
      "dollar_volume": 801025858.0
    },
    {
      "symbol": "SNDK",
      "close": 1617.7,
      "momentum_22": 1.0893,
      "momentum_67": 2.7968,
      "momentum_126": 6.074,
      "adr_pct": 9.11,
      "dollar_volume": 23613688466.0
    },
    {
      "symbol": "MRVU",
      "close": 134.33,
      "momentum_22": 1.0828,
      "momentum_67": 4.4643,
      "momentum_126": NaN,
      "adr_pct": 17.77,
      "dollar_volume": 86342944.0
    },
    {
      "symbol": "BRUN",
      "close": 29.18,
      "momentum_22": 1.0708,
      "momentum_67": 2.7451,
      "momentum_126": 2.7554,
      "adr_pct": 11.73,
      "dollar_volume": 56511156.0
    },
    {
      "symbol": "IONX",
      "close": 36.32,
      "momentum_22": 1.0682,
      "momentum_67": 2.0416,
      "momentum_126": 4.3238,
      "adr_pct": 17.46,
      "dollar_volume": 59292166.0
    },
    {
      "symbol": "TSLS",
      "close": 52.8,
      "momentum_22": 1.0634,
      "momentum_67": 1.084,
      "momentum_126": 10.6024,
      "adr_pct": 4.8,
      "dollar_volume": 40459719.0
    },
    {
      "symbol": "WOLF",
      "close": 36.0,
      "momentum_22": 1.0585,
      "momentum_67": 2.4641,
      "momentum_126": 2.6696,
      "adr_pct": 13.95,
      "dollar_volume": 296914528.0
    },
    {
      "symbol": "AEHR",
      "close": 66.94,
      "momentum_22": 1.054,
      "momentum_67": 2.0285,
      "momentum_126": 3.1516,
      "adr_pct": 11.74,
      "dollar_volume": 162760878.0
    },
    {
      "symbol": "STX",
      "close": 827.64,
      "momentum_22": 1.053,
      "momentum_67": 2.249,
      "momentum_126": 2.9804,
      "adr_pct": 7.77,
      "dollar_volume": 4717566220.0
    },
    {
      "symbol": "ARMG",
      "close": 27.78,
      "momentum_22": 1.0479,
      "momentum_67": 3.4916,
      "momentum_126": 5.9935,
      "adr_pct": 18.53,
      "dollar_volume": 73796840.0
    },
    {
      "symbol": "VSH",
      "close": 42.19,
      "momentum_22": 1.0446,
      "momentum_67": 2.5091,
      "momentum_126": 2.7414,
      "adr_pct": 9.98,
      "dollar_volume": 517728299.0
    },
    {
      "symbol": "MRVL",
      "close": 230.7,
      "momentum_22": 1.0348,
      "momentum_67": 2.4793,
      "momentum_126": 3.2638,
      "adr_pct": 8.86,
      "dollar_volume": 16557484522.0
    },
    {
      "symbol": "AMBQ",
      "close": 75.48,
      "momentum_22": 1.0344,
      "momentum_67": 3.1668,
      "momentum_126": 3.3178,
      "adr_pct": 8.38,
      "dollar_volume": 66607383.0
    },
    {
      "symbol": "AAOI",
      "close": 114.41,
      "momentum_22": 1.0261,
      "momentum_67": 1.4561,
      "momentum_126": 3.6126,
      "adr_pct": 11.92,
      "dollar_volume": 2129104879.0
    },
    {
      "symbol": "ARM",
      "close": 300.43,
      "momentum_22": 1.0219,
      "momentum_67": 2.1837,
      "momentum_126": 3.0037,
      "adr_pct": 9.22,
      "dollar_volume": 3982757963.0
    },
    {
      "symbol": "VPG",
      "close": 108.45,
      "momentum_22": 1.0183,
      "momentum_67": 2.6196,
      "momentum_126": 2.8158,
      "adr_pct": 9.25,
      "dollar_volume": 86375492.0
    },
    {
      "symbol": "NBIL",
      "close": 26.92,
      "momentum_22": 1.0158,
      "momentum_67": 3.0315,
      "momentum_126": 4.2261,
      "adr_pct": 20.18,
      "dollar_volume": 78639886.0
    }
  ]
}